{
  "parent": "minecraft:recipes/root",
  "rewards": {
    "recipes": [
      "astromine:univite_gear"
    ]
  },
  "criteria": {
    "has_univite_ingots": {
      "trigger": "minecraft:inventory_changed",
      "conditions": {
        "items": [
          {
            "tag": "c:univite_ingots"
          }
        ]
      }
    },
    "has_the_recipe": {
      "trigger": "minecraft:recipe_unlocked",
      "conditions": {
        "recipe": "astromine:univite_gear"
      }
    }
  },
  "requirements": [
    [
      "has_univite_ingots",
      "has_the_recipe"
    ]
  ]
}