{
  "parent": "minecraft:recipes/root",
  "rewards": {
    "recipes": [
      "minecraft:diamond_from_blasting_diamond_clusters"
    ]
  },
  "criteria": {
    "has_diamond_clusters": {
      "trigger": "minecraft:inventory_changed",
      "conditions": {
        "items": [
          {
            "tag": "c:diamond_clusters"
          }
        ]
      }
    },
    "has_the_recipe": {
      "trigger": "minecraft:recipe_unlocked",
      "conditions": {
        "recipe": "minecraft:diamond_from_blasting_diamond_clusters"
      }
    }
  },
  "requirements": [
    [
      "has_diamond_clusters",
      "has_the_recipe"
    ]
  ]
}