{
  "name": "text.astromine.astronautics.space_suit.title",
  "icon": "astromine:space_suit_helmet",
  "category": "astronautics",
  "sortnum": 0,
  "pages": [
    {
      "type": "spotlight",
      "item": "astromine:space_suit_helmet",
      "title": "text.astromine.astronautics.space_suit.page_one.title",
      "text": "text.astromine.astronautics.space_suit.page_one.text"
    },
    {
      "type": "crafting",
      "recipe": "astromine:space_suit_helmet",
      "recipe2": "astromine:space_suit_chestplate"
    },
    {
      "type": "crafting",
      "recipe": "astromine:space_suit_leggings",
      "recipe2": "astromine:space_suit_boots"
    }
  ]
}