{
  "parent": "minecraft:recipes/root",
  "rewards": {
    "recipes": [
      "minecraft:asterite_fragment_from_smelting_asterite_boots"
    ]
  },
  "criteria": {
    "has_asterite_boots": {
      "trigger": "minecraft:inventory_changed",
      "conditions": {
        "items": [
          {
            "items": [
              "astromine:asterite_boots"
            ]
          }
        ]
      }
    },
    "has_the_recipe": {
      "trigger": "minecraft:recipe_unlocked",
      "conditions": {
        "recipe": "minecraft:asterite_fragment_from_smelting_asterite_boots"
      }
    }
  },
  "requirements": [
    [
      "has_asterite_boots",
      "has_the_recipe"
    ]
  ]
}