{
  "variants": {
    "active=false,facing=east": {
      "model": "astromine:block/fluid_placer",
      "y": 90
    },
    "active=false,facing=north": {
      "model": "astromine:block/fluid_placer"
    },
    "active=false,facing=south": {
      "model": "astromine:block/fluid_placer",
      "y": 180
    },
    "active=false,facing=west": {
      "model": "astromine:block/fluid_placer",
      "y": 270
    },
    "active=true,facing=east": {
      "model": "astromine:block/fluid_placer_active",
      "y": 90
    },
    "active=true,facing=north": {
      "model": "astromine:block/fluid_placer_active"
    },
    "active=true,facing=south": {
      "model": "astromine:block/fluid_placer_active",
      "y": 180
    },
    "active=true,facing=west": {
      "model": "astromine:block/fluid_placer_active",
      "y": 270
    }
  }
}