{
  "parent": "minecraft:recipes/root",
  "rewards": {
    "recipes": [
      "astromine:lunum_ingot_from_lunum_blocks"
    ]
  },
  "criteria": {
    "has_lunum_blocks": {
      "trigger": "minecraft:inventory_changed",
      "conditions": {
        "items": [
          {
            "tag": "c:lunum_blocks"
          }
        ]
      }
    },
    "has_the_recipe": {
      "trigger": "minecraft:recipe_unlocked",
      "conditions": {
        "recipe": "astromine:lunum_ingot_from_lunum_blocks"
      }
    }
  },
  "requirements": [
    [
      "has_lunum_blocks",
      "has_the_recipe"
    ]
  ]
}