{
  "parent": "minecraft:recipes/root",
  "criteria": {
    "has_the_recipe": {
      "conditions": {
        "recipe": "minecraft:univite_axe_from_smithing_galaxium_axe"
      },
      "trigger": "minecraft:recipe_unlocked"
    },
    "has_univite_ingot": {
      "conditions": {
        "items": [
          {
            "items": [
              "astromine:univite_ingot"
            ]
          }
        ]
      },
      "trigger": "minecraft:inventory_changed"
    }
  },
  "requirements": [
    [
      "has_univite_ingot",
      "has_the_recipe"
    ]
  ],
  "rewards": {
    "recipes": [
      "minecraft:univite_axe_from_smithing_galaxium_axe"
    ]
  }
}